CONTRIBUTING.md
LICENSE
MANIFEST.in
Makefile
README.md
pyproject.toml
setup.py
scranking/Swimmer.py
scranking/__init__.py
scranking/_version.py
scranking.egg-info/PKG-INFO
scranking.egg-info/SOURCES.txt
scranking.egg-info/dependency_links.txt
scranking.egg-info/requires.txt
scranking.egg-info/top_level.txt
scranking/test/test_Swimmer.py
scranking/test/test_intergration.py