Metadata-Version: 2.1
Name: scranking
Version: 0.1.2
Summary: scranking is a python library that display ranking of the college swimmer
Author-email: Joon Ahn <sa3883@columbia.edu>
License: MIT License
Project-URL: repository, https://github.com/joon0110/scranking
Classifier: Development Status :: 2 - Pre-Alpha
Classifier: Programming Language :: Python :: Implementation :: CPython
Classifier: Programming Language :: Python :: Implementation :: PyPy
Classifier: Programming Language :: Python :: 3
Classifier: Programming Language :: Python :: 3.7
Classifier: Programming Language :: Python :: 3.8
Classifier: Programming Language :: Python :: 3.9
Classifier: Programming Language :: Python :: 3.10
Classifier: Programming Language :: Python :: 3.11
Requires-Python: >=3.8
Provides-Extra: develop
License-File: LICENSE
